Metadata-Version: 2.1
Name: ctdGAN
Version: 0.1.5
Summary: A Generative Adversarial Network for synthesizing artificial tabular data.
Home-page: https://github.com/lakritidis/ctdGAN
Author: Leonidas Akritidis
Author-email: lakritidis@ihu.gr
Maintainer: Leonidas Akritidis
Maintainer-email: lakritidis@ihu.gr
License: Apache
Keywords: ctdGAN,GAN,Generative Adversarial Network,imbalanced data,tabular data,deep learning
License-File: LICENSE
Requires-Dist: numpy
Requires-Dist: pandas
Requires-Dist: matplotlib
Requires-Dist: seaborn
Requires-Dist: sdv
Requires-Dist: tqdm
Requires-Dist: joblib
Requires-Dist: torch>=2.0.0
Requires-Dist: scikit-learn>=1.4.0
Requires-Dist: rdt<2.0,>=1.3.0
